{"wav_id": "101839", "speaker": "101839", "offset": "7.180", "duration": "0.570", "wav": "101839.wav", "translation": "Hello everyone.", "transcript": "大家好。"}
{"wav_id": "101839", "speaker": "101839", "offset": "8.510", "duration": "2.310", "wav": "101839.wav", "translation": "I'm Liang Jia'en, from Unisound.", "transcript": "我是梁家恩,来自云知声。"}
{"wav_id": "101839", "speaker": "101839", "offset": "11.290", "duration": "5.030", "wav": "101839.wav", "translation": "I'm a typical fan of science, and my interest in science has lasted for years ever since I was a high school student.", "transcript": "呃我是一个典型的科技爱好者，从中学开始呢就一直比较喜欢科技。"}
{"wav_id": "101839", "speaker": "101839", "offset": "16.590", "duration": "2.330", "wav": "101839.wav", "translation": "I began to know AI in university.", "transcript": "在大学的时候就开始接触这个人工智能了。"}
{"wav_id": "101839", "speaker": "101839", "offset": "19.310", "duration": "9.600", "wav": "101839.wav", "translation": "And for twenty years after that, from being a university student to getting my doctor's degree, to starting my career and finally founding my own company, I've never for a second deviated from the tracks of AI.", "transcript": "到现在为止有有二十年的时间，呃从读书到读博士学位，后来到工作，到现在的创业，一直在这行业里面就没有离开过。"}
{"wav_id": "101839", "speaker": "101839", "offset": "29.350", "duration": "9.670", "wav": "101839.wav", "translation": "The reason I, despite all the ups and downs, have always stuck to AI, is that I identify with the AI dream so profoundly and have such deep faith in it.", "transcript": "呃之所以在这个行业里面，一直在高潮和低潮的时候，一直在这边工作呢，还是因为对于这个梦想其实有一种很深的认同和和信仰。"}
{"wav_id": "101839", "speaker": "101839", "offset": "39.310", "duration": "3.540", "wav": "101839.wav", "translation": "And plus, it's indeed a field that is inexhaustible in questions.", "transcript": "同时的话这个行业也确实有永远解决不完的问题。"}
{"wav_id": "101839", "speaker": "101839", "offset": "43.040", "duration": "1.710", "wav": "101839.wav", "translation": "So there is no way for us to just quit.", "transcript": "所以的话，我们也永远没有办法去离开。"}
{"wav_id": "101839", "speaker": "101839", "offset": "45.140", "duration": "6.890", "wav": "101839.wav", "translation": "Today my topic is AI, a new species that human beings can tame.", "transcript": "那么我今天呢能给大家带来一个分享的话题，就是人工智能——人类可以驾驭的新物种。"}
{"wav_id": "101839", "speaker": "101839", "offset": "52.560", "duration": "11.290", "wav": "101839.wav", "translation": "This new species has given us many surprises, such as AlphaGo, which had swept across the globe in 2016 and left the entire world exhilarated..", "transcript": "对一个新的物种来说，大家现在能看到人工智能，特别是AlphaGo，对吧，在16年的时候横扫全球，让全全民为这个AI狂欢，让大家觉得非常的兴奋。"}
{"wav_id": "101839", "speaker": "101839", "offset": "64.110", "duration": "10.800", "wav": "101839.wav", "translation": "If you take a close look, you may find that AI, once confined in science fiction, is entering into the real world.", "transcript": "那么同时的话，如果关注人工智能行业的话，大家可以看到人工智能智能呢可能已经逐步地从我们过去在科幻的世界里面，一步一步走到了我们的现实生活当中。"}
{"wav_id": "101839", "speaker": "101839", "offset": "75.180", "duration": "3.820", "wav": "101839.wav", "translation": "Keeping surprising us and giving us new hopes.", "transcript": "那么给我们带来了很多的惊喜，对吧，也有过很多的期待。"}
{"wav_id": "101839", "speaker": "101839", "offset": "79.220", "duration": "5.190", "wav": "101839.wav", "translation": "But it also brings with it confusion, concerns, or even fears.", "transcript": "但同时的话呢，也让我们感到困惑，有些是担忧，甚至有一些恐惧。"}
{"wav_id": "101839", "speaker": "101839", "offset": "84.840", "duration": "16.830", "wav": "101839.wav", "translation": "So today, as one who has been working on AI for twenty years, I wish I could give you a professional interpretation of what exactly is going on, its origin, history, characteristic, and where it is going.", "transcript": "那么我们今天呢就希望，从一个二十年的AI工作者来说，如何从专业的角度去解读一下，我们现在究竟发生了什么事情，它的前世今生、前因后果，以及它的特点，它未来会往什么方向去演进。"}
{"wav_id": "101839", "speaker": "101839", "offset": "101.950", "duration": "5.420", "wav": "101839.wav", "translation": "Will it finally get out of human control, become the last invention by mankind and end up as the terminator of human beings?", "transcript": "它会不会脱离我们人类的控制，让我们成为我们人类最后一项发明，最后毁灭了我们人类。"}
{"wav_id": "101839", "speaker": "101839", "offset": "107.710", "duration": "2.960", "wav": "101839.wav", "translation": "That's what I'm going to talk about today.", "transcript": "那我希望对这个话题呢，跟大家做一个分享。"}
{"wav_id": "101839", "speaker": "101839", "offset": "111.980", "duration": "4.800", "wav": "101839.wav", "translation": "Personally I don't think there is anything mysterious at all about AI.", "transcript": "那么从我的角度来看，其实AI它其并不神秘。"}
{"wav_id": "101839", "speaker": "101839", "offset": "117.590", "duration": "7.550", "wav": "101839.wav", "translation": "It 's just a brand-new intelligent species that is created based on rational analysis, data and algorithms.", "transcript": "它只是我们人类呢基于我们的理性、数据、还有计算所构建出来一个全新的智慧物种。"}
{"wav_id": "101839", "speaker": "101839", "offset": "125.600", "duration": "9.900", "wav": "101839.wav", "translation": "The possibility of AI had long been talked of, yet it was Alan Turing, a household name to us all, that first seriously considered the possibility.", "transcript": "那么这个物种，这个梦想很早就开始提出来，但是真正能够把这个梦想当回事的第一个人，就是大家熟悉的阿兰·图灵。"}
{"wav_id": "101839", "speaker": "101839", "offset": "135.840", "duration": "2.560", "wav": "101839.wav", "translation": "Let's rewind the time back to eighty years ago.", "transcript": "那么我们把镜头拉回到八十年前。"}
{"wav_id": "101839", "speaker": "101839", "offset": "138.670", "duration": "8.110", "wav": "101839.wav", "translation": "In 1936, Alan Turing was thinking about letting machines think for human beings.", "transcript": "阿兰·图灵在1936年的时候呢，就开始呃想着用机器来代替人类做思维、思考这种工作。"}
{"wav_id": "101839", "speaker": "101839", "offset": "147.140", "duration": "1.700", "wav": "101839.wav", "translation": "And he actually did a research into that.", "transcript": "把它当回事来研究一下。"}
{"wav_id": "101839", "speaker": "101839", "offset": "149.150", "duration": "7.700", "wav": "101839.wav", "translation": "His earliest idea was that, when we calculate, we have to use a pen and paper.", "transcript": "那么他最早研究的就是说，我们人类开始做数学计算的时候，是用纸和笔去去做运算的。"}
{"wav_id": "101839", "speaker": "101839", "offset": "157.120", "duration": "6.270", "wav": "101839.wav", "translation": "But would it be possible that the entire process of calculating could be abstracted into a mathematical model through which problems can be solved by some machine?", "transcript": "那么这种行为是不是可以抽象成为一个数学的模型，然后呢用某种机器去解决这些问题呢？"}
{"wav_id": "101839", "speaker": "101839", "offset": "163.440", "duration": "1.310", "wav": "101839.wav", "translation": "Such machines certainly didn't exist then.", "transcript": "当时这类的机器还不存在。"}
{"wav_id": "101839", "speaker": "101839", "offset": "165.010", "duration": "4.390", "wav": "101839.wav", "translation": "He was absolutely thinking from a theoretical, mathematical perspective.", "transcript": "他完全是一个从思维的角度来考虑这个问题，从数学角度来考量。"}
{"wav_id": "101839", "speaker": "101839", "offset": "169.740", "duration": "4.020", "wav": "101839.wav", "translation": "But he did write a paper, which somehow proved what he imagined was nonetheless possible.", "transcript": "但是他真的出了一篇论文，证明这个事情是possible，对吧。"}
{"wav_id": "101839", "speaker": "101839", "offset": "173.900", "duration": "2.560", "wav": "101839.wav", "translation": "A brand-new journey was thus launched.", "transcript": "那就开启了一个全新的历程。"}
{"wav_id": "101839", "speaker": "101839", "offset": "176.760", "duration": "6.060", "wav": "101839.wav", "translation": "And  to commemorate Alan Turing, the great pioneer, the most important prize throughout the entire computer industry—Turing Award—was established.", "transcript": "所以在整个计算机行业，那么最重最重要的奖就是图灵奖，这是一开山鼻祖。"}
{"wav_id": "101839", "speaker": "101839", "offset": "183.130", "duration": "4.590", "wav": "101839.wav", "translation": "So what happened after Alan Turing put forward this idea and proved it possible?", "transcript": "那么在图灵提出这个思想，证明了这个可能性之后呢。"}
{"wav_id": "101839", "speaker": "101839", "offset": "187.830", "duration": "2.720", "wav": "101839.wav", "translation": "The first computer made its debut ten years later.", "transcript": "十年之后那么第一台计算机就出现了。"}
{"wav_id": "101839", "speaker": "101839", "offset": "190.620", "duration": "3.370", "wav": "101839.wav", "translation": "Since 1946, computers have been setting one record after another.", "transcript": "1946年，那么就开始了计算机的狂奔的旅程。"}
{"wav_id": "101839", "speaker": "101839", "offset": "194.220", "duration": "10.010", "wav": "101839.wav", "translation": "Another ten years passed, and in 1956, young academics like Marvin Minsky blazed a new trail, namely the trail of AI, which was extending into indefinite possibilities.", "transcript": "那再过了十年之后呢，以明斯基为代表的这些年轻的学者，就开始开辟了另外一条路径，就是人工智能这条路径，它一直在往前在发展的。"}
{"wav_id": "101839", "speaker": "101839", "offset": "204.440", "duration": "3.330", "wav": "101839.wav", "translation": "Minsky himself was the first Turing Award winner who specialized in AI.", "transcript": "但明斯基呢也是图灵奖在人工智能领域里面的第一人。"}
{"wav_id": "101839", "speaker": "101839", "offset": "208.130", "duration": "1.340", "wav": "101839.wav", "translation": "Therefore his influence was huge.", "transcript": "所以他影响也实际上非常大。"}
{"wav_id": "101839", "speaker": "101839", "offset": "209.860", "duration": "11.230", "wav": "101839.wav", "translation": "As you can see, 62 years into AI development, we have got AlphoGo who outperformed human professional Go players, and the entire AI industry is going through tremendous changes.", "transcript": "那么大家可以看到，整个呃六十年的发展到现在已经62年了，在在击败AlphaGo的话是六十年的发展，那整个人工智能呢得到翻天覆地的变化。"}
{"wav_id": "101839", "speaker": "101839", "offset": "221.340", "duration": "8.640", "wav": "101839.wav", "translation": "As for the ordinary internet users and media, they are more susceptible to changes in the computer industry, especially in the internet industry.", "transcript": "那么我们一般的用户和媒体呢，感受得到的更多的是说在计算机行业，以及特别是在互联网行业，可以给我们带来的影响和变化。"}
{"wav_id": "101839", "speaker": "101839", "offset": "230.440", "duration": "4.730", "wav": "101839.wav", "translation": "So far, AI industry has actually hit two peaks and bottoms.", "transcript": "那么人工智能行业，其实在底下呢发生了一个两次的两两起两落。"}
{"wav_id": "101839", "speaker": "101839", "offset": "235.620", "duration": "3.580", "wav": "101839.wav", "translation": "The third peak for AI, as we can see, is just breaking out all of a sudden.", "transcript": "那么这第三次浪潮，为什么大家觉得说一下就引爆了。"}
{"wav_id": "101839", "speaker": "101839", "offset": "239.360", "duration": "3.040", "wav": "101839.wav", "translation": "That's because the previous accumulation has laid a solid foundation for it.", "transcript": "其实是因为前面的这个积累所所造成的。"}
{"wav_id": "101839", "speaker": "101839", "offset": "242.980", "duration": "8.680", "wav": "101839.wav", "translation": "But why, given the two previous troughs, are we still confident that a new species will be born in the third AI peak?", "transcript": "那么我们前面为什么前面两次浪潮它会处于低谷，那么第三次浪潮，我们为什么这么有信心，认为一个新的物种，它会诞生呢？"}
{"wav_id": "101839", "speaker": "101839", "offset": "252.250", "duration": "3.280", "wav": "101839.wav", "translation": "Let me use some figures to help you understand.", "transcript": "这我们就可以看一下下面这个数据，应该就可以帮大家理解。"}
{"wav_id": "101839", "speaker": "101839", "offset": "256.960", "duration": "5.450", "wav": "101839.wav", "translation": "First we think this third AI peak comes at a perfect moment that combines all kinds of favorable conditions.", "transcript": "首先我们认为这一个第三次浪潮，应该堪称天时地利人和，绝佳的时机。"}
{"wav_id": "101839", "speaker": "101839", "offset": "262.670", "duration": "5.200", "wav": "101839.wav", "translation": "The No. 1 advantage we now have is the unprecedented computing power.", "transcript": "我们先看天时，天时第一点就是看计算能力，计算能力大家都可以知道。"}
{"wav_id": "101839", "speaker": "101839", "offset": "267.930", "duration": "2.450", "wav": "101839.wav", "translation": "Take this Huawei P9 for example.", "transcript": "像我们手上拿一个华为的P9，对吧。"}
{"wav_id": "101839", "speaker": "101839", "offset": "270.650", "duration": "2.590", "wav": "101839.wav", "translation": "It is portable and highly energy efficient.", "transcript": "其实是可以揣在兜里面的，嗯很低功耗的。"}
{"wav_id": "101839", "speaker": "101839", "offset": "273.620", "duration": "5.710", "wav": "101839.wav", "translation": "Now suppose we traveled with it back to 1974, five years after the first moon landing.", "transcript": "但是这个P9的话，假如我们穿越回去到1974年的时候，人类登月回来已经五年了。"}
{"wav_id": "101839", "speaker": "101839", "offset": "279.720", "duration": "7.050", "wav": "101839.wav", "translation": "We would find people were still using Intel's flagship 8080 microprocessor, which, trust me, would be seckilled by this Huawei P9.", "transcript": "那么我们看当时的intel的旗舰级芯片8080，跟它相比的话，20万倍的秒杀，对吧。"}
{"wav_id": "101839", "speaker": "101839", "offset": "286.830", "duration": "5.100", "wav": "101839.wav", "translation": "If we could time-travel to that time, scientists back then would treat us like god.", "transcript": "那如果我们到穿越到那个时候的话，相信那个时候的科学家，会把我们当成天神来看待。"}
{"wav_id": "101839", "speaker": "101839", "offset": "292.070", "duration": "1.070", "wav": "101839.wav", "translation": "That would be so cool.", "transcript": "对吧，也就非常厉害的。"}
{"wav_id": "101839", "speaker": "101839", "offset": "293.580", "duration": "1.480", "wav": "101839.wav", "translation": "What I want to say is: the computing power today has achieved a new high.", "transcript": "所以现在就是计算的进步。"}
{"wav_id": "101839", "speaker": "101839", "offset": "295.250", "duration": "2.710", "wav": "101839.wav", "translation": "Next, let's take a look at data.", "transcript": "那么下一步就是我们的数据，然后呢我们看。"}
{"wav_id": "101839", "speaker": "101839", "offset": "298.270", "duration": "2.630", "wav": "101839.wav", "translation": "Data is increasing by millions of TB every day.", "transcript": "每天都是上百万T的这种数据的积累。"}
{"wav_id": "101839", "speaker": "101839", "offset": "301.080", "duration": "3.040", "wav": "101839.wav", "translation": "That was never seen at the first and second peak.", "transcript": "那在过去第一跟第二次浪潮里面，这是没有的。"}
{"wav_id": "101839", "speaker": "101839", "offset": "304.210", "duration": "2.780", "wav": "101839.wav", "translation": "After all, there was no internet then, thus we couldn't get much true information about the computer users.", "transcript": "当时还没有互联网对吧，都没有真实的用户数据。"}
{"wav_id": "101839", "speaker": "101839", "offset": "307.630", "duration": "3.550", "wav": "101839.wav", "translation": "Then there are also the dividends of the computing power, or the technological accumulation.", "transcript": "那么后面这个是一个计算的这种红利的，就技术的积累。"}
{"wav_id": "101839", "speaker": "101839", "offset": "311.420", "duration": "5.290", "wav": "101839.wav", "translation": "We can see some people never talk about AI without emphasizing deep learning, as if a man ignoring deep learning would know nothing about AI.", "transcript": "那么大家现在一谈到人工智能就言必称深度学习，好像不谈深度学习，就不懂人工智能。"}
{"wav_id": "101839", "speaker": "101839", "offset": "317.030", "duration": "7.870", "wav": "101839.wav", "translation": "This school of AI academics is in fact, to put it simply, advocating stimulating the neural network of human brain so as to solve problems concerning human intelligence.", "transcript": "那么这个学派呢其实很简单的思路就是说，能不能模拟人脑的这种神经网络，去解决一下人人的这种智能问题。"}
{"wav_id": "101839", "speaker": "101839", "offset": "324.940", "duration": "1.160", "wav": "101839.wav", "translation": "That is a very natural idea.", "transcript": "这是非常自然的想法。"}
{"wav_id": "101839", "speaker": "101839", "offset": "326.500", "duration": "9.170", "wav": "101839.wav", "translation": "And that idea has been implemented and developed ever since 1943, when the single neuron was abstracted into and displayed by a mathematical model.", "transcript": "那么这个朴素的想法，在1943年的时候呢，就已经用数学模型，把那个单个的神经元给抽象出来了，那么到一直发展到今天。"}
{"wav_id": "101839", "speaker": "101839", "offset": "335.900", "duration": "3.910", "wav": "101839.wav", "translation": "A great moment for AI has come, because we have got the great computing power, great storage capacity and great technologies.", "transcript": "所以我们说天时是包括计算、存储和我们的技术能力。"}
{"wav_id": "101839", "speaker": "101839", "offset": "340.250", "duration": "7.700", "wav": "101839.wav", "translation": "The second favorable condition is the internet of things, which, combined with the Internet, is giving AI full play.", "transcript": "那么地利来说的话，就是整个物联网，还有我们的互联网发展，那为整个AI提供了非常广阔的用武之地。"}
{"wav_id": "101839", "speaker": "101839", "offset": "348.160", "duration": "1.100", "wav": "101839.wav", "translation": "That's a great platform for AI.", "transcript": "这是我们一个地利。"}
{"wav_id": "101839", "speaker": "101839", "offset": "349.950", "duration": "3.720", "wav": "101839.wav", "translation": "But the most important condition is the support from the government and the people.", "transcript": "那最重要的还是人和，那么人和从政府的角度来说。"}
{"wav_id": "101839", "speaker": "101839", "offset": "353.710", "duration": "4.170", "wav": "101839.wav", "translation": "The third high tide of AI, led by China and US, I believe, will sweep across the globe.", "transcript": "全球中美主导的这一轮浪潮，我相信席卷全球。"}
{"wav_id": "101839", "speaker": "101839", "offset": "357.980", "duration": "5.550", "wav": "101839.wav", "translation": "So far many countries have already joined in the AI development, among which China and US are the two biggest players.", "transcript": "现在很多的国家政府，已经加入到这一一个战略，那么布局最大的还是中国跟美国。"}
{"wav_id": "101839", "speaker": "101839", "offset": "363.770", "duration": "5.290", "wav": "101839.wav", "translation": "China excels in application, while US is taking the lead in basic-level technical innovation.", "transcript": "中国在应用层层方面是领先的，美国在底层这种技术创新上面，是独步全球。"}
{"wav_id": "101839", "speaker": "101839", "offset": "369.310", "duration": "2.480", "wav": "101839.wav", "translation": "For now, they seem to be even in the AI battlefield.", "transcript": "所以现在来说的话，是胜负各半吧。"}
{"wav_id": "101839", "speaker": "101839", "offset": "372.030", "duration": "1.110", "wav": "101839.wav", "translation": "I believe there is huge room for both for further development.", "transcript": "我相信大都有机会。"}
{"wav_id": "101839", "speaker": "101839", "offset": "373.550", "duration": "12.350", "wav": "101839.wav", "translation": "With the government support, the competitive field of AI development is also attracting throngs of startups, professionals and industrial investments.", "transcript": "那么在政府的推动之下呢，其实产业巨头，还有我们的创业公司，还有专业人才，还有产业资本，都在加入到这个竞争行业当中，就一时间非常热闹。"}
{"wav_id": "101839", "speaker": "101839", "offset": "386.060", "duration": "8.110", "wav": "101839.wav", "translation": "All those favorable conditions are convincing us of a prospect that the third AI peak will be completely different from the previous ones.", "transcript": "那么在这么多的天时、地利、人和之下，那我们非常有理由认为，这一轮的第三次浪潮，是跟过去是完全不一样的。"}
{"wav_id": "101839", "speaker": "101839", "offset": "394.550", "duration": "7.110", "wav": "101839.wav", "translation": "A whole new species will be born out of the combination of our rationality, data and computing.", "transcript": "它会诞生一个全新的物种，这个物种是基于我们的理性、数据和计算所构建起来的。"}
{"wav_id": "101839", "speaker": "101839", "offset": "403.810", "duration": "3.240", "wav": "101839.wav", "translation": "How should we judge this new species?", "transcript": "那么我们看一个全新的物种的时候呢，应该怎么去判断它？"}
{"wav_id": "101839", "speaker": "101839", "offset": "407.370", "duration": "1.820", "wav": "101839.wav", "translation": "Let's begin with its genes.", "transcript": "就首先要从它的基因开始看起。"}
{"wav_id": "101839", "speaker": "101839", "offset": "409.660", "duration": "0.820", "wav": "101839.wav", "translation": "Where is it going?", "transcript": "它会怎么发展？"}
{"wav_id": "101839", "speaker": "101839", "offset": "410.520", "duration": "0.980", "wav": "101839.wav", "translation": "What traits does it have?", "transcript": "会有什么特性？"}
{"wav_id": "101839", "speaker": "101839", "offset": "411.770", "duration": "6.270", "wav": "101839.wav", "translation": "The rationality, data and computing I just mentioned can be transformed to mathematical terms.", "transcript": "那我们说前面说理性跟数据跟计算，我们可以把它拆成相对比较数学一点的术语。"}
{"wav_id": "101839", "speaker": "101839", "offset": "418.380", "duration": "1.350", "wav": "101839.wav", "translation": "The first is mathematical model.", "transcript": "就是第一个是数学模型。"}
{"wav_id": "101839", "speaker": "101839", "offset": "420.100", "duration": "6.340", "wav": "101839.wav", "translation": "Whatever problem we want to solve, we must first abstract it into something in mathematics so that it could be addressed by the machines.", "transcript": "就是我们究竟要解决一个什么样的问题，我们必须把它抽象出来，变成数学上可以描述的问题，机器才能解决。"}
{"wav_id": "101839", "speaker": "101839", "offset": "426.810", "duration": "8.130", "wav": "101839.wav", "translation": "Once the abstract model is produced, we must make it work and keep improving it, thus we need algorithms.", "transcript": "那么第二个是当它抽象出来之后呢，我们能不能用让它越来越越来越好，学得越来越好，这就是算法，对吧。"}
{"wav_id": "101839", "speaker": "101839", "offset": "435.010", "duration": "4.550", "wav": "101839.wav", "translation": "And algorithms must depend on data to work at their best.", "transcript": "算法所依赖的东西就是数据，它是从数据里面汲取营养去学习的。"}
{"wav_id": "101839", "speaker": "101839", "offset": "439.960", "duration": "5.410", "wav": "101839.wav", "translation": "And all of the three steps above must be based on a reliable computing power.", "transcript": "那么这三个工作，其实都要基于我们非常强大的计算能力，才有可能去做这个工作。"}
{"wav_id": "101839", "speaker": "101839", "offset": "445.580", "duration": "1.650", "wav": "101839.wav", "translation": "That's why AlphoGo is so good.", "transcript": "所以像AlphaGo一样，为什么这么厉害？"}
{"wav_id": "101839", "speaker": "101839", "offset": "447.370", "duration": "5.310", "wav": "101839.wav", "translation": "And its successor, AlphaZero, is said to even have become independent from data resources, for it can simulate them by itself.", "transcript": "对吧，AlphaGo说AlphaZero已经可以把数据干掉了，对吧，它就可以自己做模拟数据源。"}
{"wav_id": "101839", "speaker": "101839", "offset": "452.710", "duration": "4.370", "wav": "101839.wav", "translation": "After all, the moves on a chess board are predictable, and that makes the input of external data no longer necessary.", "transcript": "因为棋盘是一个大家可以推测出来的，不需要外界再输入数据，对吧。"}
{"wav_id": "101839", "speaker": "101839", "offset": "457.120", "duration": "6.520", "wav": "101839.wav", "translation": "That is an example of how we've built a species by combining a mathematical model, algorithms, data and computing.", "transcript": "所以这就是通过数数学模型，算法还有我们的数据跟计算，打造这样一个生物。"}
{"wav_id": "101839", "speaker": "101839", "offset": "463.850", "duration": "5.810", "wav": "101839.wav", "translation": "Such a new species, as long as we keep pushing it forward, will go on evolving.", "transcript": "那么这就决定了的，只要我们给它施加这些影响，他就会演进它就会持续演进。"}
{"wav_id": "101839", "speaker": "101839", "offset": "469.710", "duration": "3.130", "wav": "101839.wav", "translation": "And technical advances and data accumulation will step up its evolution.", "transcript": "那么技术的进展跟数据的积累，将会加速它的发展。"}
{"wav_id": "101839", "speaker": "101839", "offset": "474.970", "duration": "7.530", "wav": "101839.wav", "translation": "AI as a new species is very much like a child who is amazingly good at computing.", "transcript": "那么这个人工智能这个新的物种，它其实就是像我们的一个小孩一样的，是一个理工能力非常强，对吧。"}
{"wav_id": "101839", "speaker": "101839", "offset": "482.550", "duration": "7.750", "wav": "101839.wav", "translation": "It is diligent and hard-working, always in the middle of computing and learning from the data it is provided with.", "transcript": "勤奋好学，勤奋就一个人用机器不断地停不停地计算；那么学习的话，就不同的从不断的从那个数据里面汲取营养。"}
{"wav_id": "101839", "speaker": "101839", "offset": "490.640", "duration": "5.050", "wav": "101839.wav", "translation": "And its mathematical talent lies in its great capability to abstract and compute.", "transcript": "那么它所谓的数学天才，就在它的抽象能力，跟算法能力上面。"}
{"wav_id": "101839", "speaker": "101839", "offset": "496.140", "duration": "9.630", "wav": "101839.wav", "translation": "As it grows up, this child must receive enough nutrition from the government, businesses and individuals.", "transcript": "那么我们要把这个小孩养大的话呢，其实就需要我们从政府层面、从企业层面、从个人层面，给它输送很多的营养，才能把养大。"}
{"wav_id": "101839", "speaker": "101839", "offset": "506.000", "duration": "4.690", "wav": "101839.wav", "translation": "Today's AI has already possessed a very high degree of sensory acuity.", "transcript": "那么现在的人工智能呢，其实已经逐步具备了一个非常强的这种感知能力。"}
{"wav_id": "101839", "speaker": "101839", "offset": "510.990", "duration": "6.260", "wav": "101839.wav", "translation": "Its visual and auditory sense is approaching or even outperforming that of human beings.", "transcript": "它的感知能力呢，就是现在在视觉和听觉来说，已经接近甚至于超过人类的水平了。"}
{"wav_id": "101839", "speaker": "101839", "offset": "517.560", "duration": "6.840", "wav": "101839.wav", "translation": "But on the other hand, its cognitive ability is perhaps even less than that of a primary school student, for it can't understand the content.", "transcript": "但是认知的能力，现在可能还没有达到，像我们说的小学生的水平，因为它不能理解这里面是什么内容。"}
{"wav_id": "101839", "speaker": "101839", "offset": "524.850", "duration": "2.120", "wav": "101839.wav", "translation": "But it's just a matter of time.", "transcript": "那么这个只是一个时间的问题。"}
{"wav_id": "101839", "speaker": "101839", "offset": "527.100", "duration": "4.360", "wav": "101839.wav", "translation": "When it has gained better sensory and cognitive abilities, it will show signs of maturation and begin to repay the society.", "transcript": "当它有感知、认知能力之后呢，它逐步长大才开始回馈我们这社会。"}
{"wav_id": "101839", "speaker": "101839", "offset": "531.880", "duration": "8.140", "wav": "101839.wav", "translation": "It will then provide the society with positive services, and the social resources, in return, will further enhance AI development.", "transcript": "所以这时开始为社会提供服务，因为在这种形成正向服务的情况下，那我们的社会资源还会再加持这个人工智能研究。"}
{"wav_id": "101839", "speaker": "101839", "offset": "540.230", "duration": "1.370", "wav": "101839.wav", "translation": "Thus there will be a cycle of positivity.", "transcript": "就会形成一个正向的循环。"}
{"wav_id": "101839", "speaker": "101839", "offset": "541.890", "duration": "3.910", "wav": "101839.wav", "translation": "That's what I think concerning where AI is going.", "transcript": "所以我们认为这个物种，它的演进是这样一个态势。"}
{"wav_id": "101839", "speaker": "101839", "offset": "546.730", "duration": "8.700", "wav": "101839.wav", "translation": "So, will this new species, just like all the other species on the Earth, follow certain rules of survival?", "transcript": "嗯，那么这个物种的出现，它是不是像我们地球上的其他物种一样，会遵从一些生存的法则呢？"}
{"wav_id": "101839", "speaker": "101839", "offset": "555.570", "duration": "2.310", "wav": "101839.wav", "translation": "My answer is a definite yes.", "transcript": "我们认为是一定会呀。"}
{"wav_id": "101839", "speaker": "101839", "offset": "558.250", "duration": "1.370", "wav": "101839.wav", "translation": "There are three rules AI must obey.", "transcript": "我大概归纳的有三点。"}
{"wav_id": "101839", "speaker": "101839", "offset": "560.450", "duration": "1.460", "wav": "101839.wav", "translation": "First, be efficient.", "transcript": "第一点是一个高效。"}
{"wav_id": "101839", "speaker": "101839", "offset": "562.450", "duration": "2.910", "wav": "101839.wav", "translation": "It must precisely and instantly tackle human beings' problems.", "transcript": "就它一定要能够精准跟快速地解决人的问题。"}
{"wav_id": "101839", "speaker": "101839", "offset": "565.770", "duration": "2.930", "wav": "101839.wav", "translation": "That is also a basic function we expect of it.", "transcript": "这是大家对人工智能最基本的一个期待。"}
{"wav_id": "101839", "speaker": "101839", "offset": "569.130", "duration": "3.100", "wav": "101839.wav", "translation": "It can't survive with a low efficiency.", "transcript": "假如效率很低，那这个事情现在不能存活下来。"}
{"wav_id": "101839", "speaker": "101839", "offset": "573.100", "duration": "1.430", "wav": "101839.wav", "translation": "Second, it must provide rich experiences for us.", "transcript": "那么第二点就是丰富。"}
{"wav_id": "101839", "speaker": "101839", "offset": "575.110", "duration": "11.190", "wav": "101839.wav", "translation": "If AI just means a monotonous kind of command control, then however precise and efficient it is, without rich offerings of experience it will never survive.", "transcript": "大家知道一个非常单调，如果只是一个command control，对吧，虽然很准，能解决一些效率的问题，但是它不能给我们带来很多的呃丰富的体验，那这个生物它也是不能存活下来的。"}
{"wav_id": "101839", "speaker": "101839", "offset": "586.690", "duration": "5.780", "wav": "101839.wav", "translation": "What we need is more diversified and personalized contents and services from it.", "transcript": "我们想要的其实是说它能真正的给我们带来内容跟服务，能够更加多样和个性化。"}
{"wav_id": "101839", "speaker": "101839", "offset": "592.880", "duration": "2.120", "wav": "101839.wav", "translation": "That's important.", "transcript": "所以这是一个准则。"}
{"wav_id": "101839", "speaker": "101839", "offset": "595.220", "duration": "3.890", "wav": "101839.wav", "translation": "The third important rule is that AI must give us warm feelings.", "transcript": "那么第三点也是很重要，其实就是一个所谓的有温度。"}
{"wav_id": "101839", "speaker": "101839", "offset": "599.730", "duration": "0.970", "wav": "101839.wav", "translation": "What does that mean?", "transcript": "温度代表什么呢？"}
{"wav_id": "101839", "speaker": "101839", "offset": "600.880", "duration": "4.130", "wav": "101839.wav", "translation": "It means AI must understand and show love to us human beings.", "transcript": "就代表着对我们人类的理解，和对我们人类的一个关怀。"}
{"wav_id": "101839", "speaker": "101839", "offset": "605.410", "duration": "13.190", "wav": "101839.wav", "translation": "Only when AI stops looking so cold will we human beings feel willing to dedicate ourselves to it, thereby giving it a chance to survive, improve and develop.", "transcript": "只有当这个AI的机器它变成一个不是那么冷冰冰的物种的时候呢，它才有一个生存和发展的这个机会，我们人类才会愿意为这样一个事情付出我们的努力，能让它变得越来越好。"}
{"wav_id": "101839", "speaker": "101839", "offset": "621.400", "duration": "10.640", "wav": "101839.wav", "translation": "So if this new species keeps evolving and finally fits into our society, what will it bring to us?", "transcript": "那么这个物种当它一直在演进发展过程呢，它未来会会融入到我们的社会当中，那么它对我们人类会带来一个什么样的改变？"}
{"wav_id": "101839", "speaker": "101839", "offset": "632.580", "duration": "5.600", "wav": "101839.wav", "translation": "Will it just become an ordinary device like in the past, or will it be a game-changer?", "transcript": "它究竟是一个就是一个像过去的一般的设备的存在，还是一个颠覆性的设备存在？"}
{"wav_id": "101839", "speaker": "101839", "offset": "638.510", "duration": "4.830", "wav": "101839.wav", "translation": "I'll side with the latter. AI will usher in decisive and profound changes to the human beings.", "transcript": "我们认为它对人类的影响一定是一个决定性的和根本性的变革。"}
{"wav_id": "101839", "speaker": "101839", "offset": "643.740", "duration": "1.690", "wav": "101839.wav", "translation": "Here we may sum up those changes from two aspects.", "transcript": "那可以从两个方面来看。"}
{"wav_id": "101839", "speaker": "101839", "offset": "645.880", "duration": "1.210", "wav": "101839.wav", "translation": "Number one, liberation.", "transcript": "第一点就是解放。"}
{"wav_id": "101839", "speaker": "101839", "offset": "647.420", "duration": "13.200", "wav": "101839.wav", "translation": "Ever since Alan Turing, AI has always been imagined and designed as a substitute for men during the easy, repeated or monotonous work.", "transcript": "因为我们从图灵开始，其实设计这个AI的产品就希望它有一天能代替我们去解决我们所那些简单、或者重复、或者非常枯燥的脑力劳动。"}
{"wav_id": "101839", "speaker": "101839", "offset": "660.690", "duration": "2.130", "wav": "101839.wav", "translation": "It will just free us, right?", "transcript": "我们就不需要再去做了，对吧？"}
{"wav_id": "101839", "speaker": "101839", "offset": "662.850", "duration": "5.210", "wav": "101839.wav", "translation": "Actually we have already launched a such project in Peking Union Medical College Hospital.", "transcript": "这样的工作其实我们在呃我们实践当中呢是我们跟协和医院去合作。"}
{"wav_id": "101839", "speaker": "101839", "offset": "668.110", "duration": "2.540", "wav": "101839.wav", "translation": "Doctors in Beijing normally get off work around 16:30.", "transcript": "在北京的医生的话，是每天是四点半就下班了。"}
{"wav_id": "101839", "speaker": "101839", "offset": "671.000", "duration": "6.800", "wav": "101839.wav", "translation": "But that doesn't mean they can go home at once, for they have to spend another three to four hours in sorting through the medical records at the hospital.", "transcript": "但他下班之后呢其实并不是说我马上就可以回家了，他还需要花大概有三到四个小时的时间去整理这个病例。"}
{"wav_id": "101839", "speaker": "101839", "offset": "678.190", "duration": "3.640", "wav": "101839.wav", "translation": "It's a terribly time-consuming job, but it's also necessary.", "transcript": "整理病例花的时间实际上非常多，因为这个是他必须要做的工作。"}
{"wav_id": "101839", "speaker": "101839", "offset": "682.210", "duration": "8.890", "wav": "101839.wav", "translation": "In this project we provided the voice recognition technology for the hospital, which enabled the doctors to record as he worked.", "transcript": "那么我们其实给他提供了一个这个语音的这种病例的录入，那么他在一边工作的时候就一边录入他就就整理下来。"}
{"wav_id": "101839", "speaker": "101839", "offset": "691.340", "duration": "4.540", "wav": "101839.wav", "translation": "The original three to four hours were instantly reduced to one hour or so.", "transcript": "当然他就可以把他嘶大概有三四个小时时间一下子缩短到一个多小时的时间。"}
{"wav_id": "101839", "speaker": "101839", "offset": "696.210", "duration": "1.540", "wav": "101839.wav", "translation": "That's what I mean about liberation.", "transcript": "那这样来说就可以解放了很多。"}
{"wav_id": "101839", "speaker": "101839", "offset": "697.900", "duration": "6.880", "wav": "101839.wav", "translation": "The easy job of sorting through medical records occupies a disproportionate share of the time of the professional doctors, but the job can't be shirked.", "transcript": "因为这些工作来说其实它完全不需要像医生这样一个专业度很高的人去处理这些事情，但是呢它又必须不得不做。"}
{"wav_id": "101839", "speaker": "101839", "offset": "705.080", "duration": "5.780", "wav": "101839.wav", "translation": "AI lifts the doctors out of the tedious labor and helps them spare time for more valuable things.", "transcript": "所以这就从解放的角度，能把人类给释放出来，让他做更有价值的工作，这是第一个部分。"}
{"wav_id": "101839", "speaker": "101839", "offset": "711.280", "duration": "9.260", "wav": "101839.wav", "translation": "The second change AI will cause might be more exhilarating, for according to human beings, every time a new machine appears, human intelligence will be extended.", "transcript": "那么第二部分来说，可能是大家更值得期待的，因为我们认为当一个新的机器出现的时候，它就会延伸我们人类的这种脑力的能力。"}
{"wav_id": "101839", "speaker": "101839", "offset": "720.810", "duration": "2.690", "wav": "101839.wav", "translation": "It's like we've got an intellectual telescope.", "transcript": "这个可以比喻为就像我们看到一个望远镜。"}
{"wav_id": "101839", "speaker": "101839", "offset": "723.870", "duration": "4.920", "wav": "101839.wav", "translation": "Before the telescope we could only look at the sky or the earth with our own eyes.", "transcript": "过去我们没有望远镜的时候，我们只能肉眼看看天空，对吧，然后眼睛看看这个地上。"}
{"wav_id": "101839", "speaker": "101839", "offset": "729.070", "duration": "1.420", "wav": "101839.wav", "translation": "Our view was quite limited.", "transcript": "那我们看到的东西只是有限的。"}
{"wav_id": "101839", "speaker": "101839", "offset": "730.820", "duration": "7.530", "wav": "101839.wav", "translation": "But facilities like the telescope now extend our sight into the space a billion light years beyond.", "transcript": "那当我们有了很多设备之后呢，我们可以看到呃数十亿光年之外的这种星球它到底什么样子，这就是对我们人类的延伸。"}
{"wav_id": "101839", "speaker": "101839", "offset": "738.450", "duration": "4.180", "wav": "101839.wav", "translation": "In future, mankind must also have the ability to discern things from the big data.", "transcript": "未来我们还需要一种能力就是我们透视这个大数据的能力。"}
{"wav_id": "101839", "speaker": "101839", "offset": "743.120", "duration": "4.050", "wav": "101839.wav", "translation": "The entire Internet is backed by mountains of data, but what exactly do those data mean?", "transcript": "整个互联网背后其实有非常多的数据，但是数据背后代表什么？"}
{"wav_id": "101839", "speaker": "101839", "offset": "747.620", "duration": "1.110", "wav": "101839.wav", "translation": "Perhaps nobody knows.", "transcript": "我们可能没有人知道。"}
{"wav_id": "101839", "speaker": "101839", "offset": "749.300", "duration": "10.440", "wav": "101839.wav", "translation": "For example, when we were developing the automotive navigation products, we took it for granted that those products must be a No.1 rigid demand, for the drivers must need them.", "transcript": "就我们在做车载导航的这种产品的时候呢，我们就会发现我们一直以为说在开车里面，导航一定是一个刚需的产品，对吧，排名第一的，因为开车么必须要导航。"}
{"wav_id": "101839", "speaker": "101839", "offset": "759.970", "duration": "3.800", "wav": "101839.wav", "translation": "But as time went, we found that automotive navigation could only rank the 3rd or 4th among all demands.", "transcript": "但最近我们发现下来，这个需求其实可能只排名到第三跟第四。"}
{"wav_id": "101839", "speaker": "101839", "offset": "764.290", "duration": "5.100", "wav": "101839.wav", "translation": "Then we began to realize that, actually, most people just drive cars to and from work.", "transcript": "后面我们就开始理解这个事情，对吧，因为大多数人开车他其实就上班、下班。"}
{"wav_id": "101839", "speaker": "101839", "offset": "769.640", "duration": "2.550", "wav": "101839.wav", "translation": "On those occasions they don't need navigation instructions at all.", "transcript": "完全不需要说导航告诉我怎么去走这个路径。"}
{"wav_id": "101839", "speaker": "101839", "offset": "772.360", "duration": "4.080", "wav": "101839.wav", "translation": "They only need them when they are going to a new location.", "transcript": "只有他去到一个比较陌生的地方的时候，他可能才需要说用这样一个功能。"}
{"wav_id": "101839", "speaker": "101839", "offset": "776.890", "duration": "8.450", "wav": "101839.wav", "translation": "So the big data will change our stereotyped understanding about things, and lead us to think from different perspectives and at a deeper level.", "transcript": "所以的话它会改变我们对一个事物的一个既定的认知，我们从不同的视角，更深的深度去理解我们这个世界。"}
{"wav_id": "101839", "speaker": "101839", "offset": "785.780", "duration": "4.110", "wav": "101839.wav", "translation": "Those are the two major changes I think AI will bring to human society.", "transcript": "所以呢从这两点来看，它会对我们人类的社会产生更深刻的变革。"}
{"wav_id": "101839", "speaker": "101839", "offset": "790.160", "duration": "4.510", "wav": "101839.wav", "translation": "And they will exert massive influence on the entire society.", "transcript": "它发生变革之后呢，对这个社会带来的影响是非常巨大的。"}
{"wav_id": "101839", "speaker": "101839", "offset": "794.920", "duration": "7.280", "wav": "101839.wav", "translation": "Growing human cognition about science, AI and big data, I believe, in particular, will lead to revolutionary changes.", "transcript": "特别像前面的科学的认知和现在的整个人工智能和大数据这种认知，我相信这种认知是一个颠覆性的变化。"}
{"wav_id": "101839", "speaker": "101839", "offset": "803.130", "duration": "4.320", "wav": "101839.wav", "translation": "But will AI get out of control and become unmanageable?", "transcript": "那么将来它会不会真的是脱离我们的控制让我们无法驾驭呢？"}
{"wav_id": "101839", "speaker": "101839", "offset": "807.820", "duration": "7.810", "wav": "101839.wav", "translation": "We mustn't be arbitrary on that. Instead, we must return to its genes and methodology to find the right answer.", "transcript": "那么这个问题，我们其实还是要回到这个AI它本身的基因和方法论上来考虑，我们不能笼统地说它行还是不行。"}
{"wav_id": "101839", "speaker": "101839", "offset": "815.860", "duration": "6.120", "wav": "101839.wav", "translation": "As I mentioned earlier in my speech today, AI is defined as a mathematical model that helps men solve problems.", "transcript": "刚才前面已经拆解过了，就它是一个数学模型的定义，数学模型就是它所需要解决什么问题。"}
{"wav_id": "101839", "speaker": "101839", "offset": "822.270", "duration": "5.430", "wav": "101839.wav", "translation": "It depends on algorithms to learn and improve its problem solving ability.", "transcript": "那么在学习方法就是如何能让它所学习解决问题，能越解决越好，这是算法的部分工作。"}
{"wav_id": "101839", "speaker": "101839", "offset": "827.880", "duration": "7.420", "wav": "101839.wav", "translation": "This learning process of AI reinforced by big data and super computing is the strongest part of it, and yet it is completely controllable for us.", "transcript": "那么它威力最强大的部分就是用大数据和超级计算去加速它这个学习过程，对这块来说我们人类是完全可控的。"}
{"wav_id": "101839", "speaker": "101839", "offset": "835.770", "duration": "5.140", "wav": "101839.wav", "translation": "So I'm convinced that this new species is one we can absolutely manage.", "transcript": "所以我们认为这个新的物种的存在，它其实是一个我们可以驾驭的物种。"}
{"wav_id": "101839", "speaker": "101839", "offset": "840.980", "duration": "2.860", "wav": "101839.wav", "translation": "It is not so scary as we have imagined, but rather, quite amiable.", "transcript": "并不像我们想象那么恐怖，它其实还是非常亲切的。"}
{"wav_id": "101839", "speaker": "101839", "offset": "844.390", "duration": "3.480", "wav": "101839.wav", "translation": "Based on the foregoing, I've reached two conclusions.", "transcript": "那么基于这些的理解呢，我们得出两个重要的结论。"}
{"wav_id": "101839", "speaker": "101839", "offset": "848.370", "duration": "3.470", "wav": "101839.wav", "translation": "First, AI itself is not evil.", "transcript": "就是AI本身呢，它其实内心是没有鬼的。"}
{"wav_id": "101839", "speaker": "101839", "offset": "854.430", "duration": "0.240", "wav": "101839.wav", "translation": "You agree with me, right?", "transcript": "对？"}
{"wav_id": "101839", "speaker": "101839", "offset": "855.020", "duration": "2.130", "wav": "101839.wav", "translation": "AI itself is not evil.", "transcript": "AI心中是本无鬼。"}
{"wav_id": "101839", "speaker": "101839", "offset": "857.460", "duration": "2.340", "wav": "101839.wav", "translation": "It is human who may be evil.", "transcript": "那么所有的鬼都在人身上，对吧。"}
{"wav_id": "101839", "speaker": "101839", "offset": "859.850", "duration": "4.350", "wav": "101839.wav", "translation": "Whether AI will benefit or destroy mankind is completely decided by men themselves.", "transcript": "它将来到底会作恶，还是会造福人类，完全取决人类本身。"}
{"wav_id": "101839", "speaker": "101839", "offset": "864.510", "duration": "4.550", "wav": "101839.wav", "translation": "So controlling the risks of AI is in fact a problem of controlling people.", "transcript": "所以它的风险，其实最根本的还是要回到这如何控制人的风险上面。"}
{"wav_id": "101839", "speaker": "101839", "offset": "869.430", "duration": "2.950", "wav": "101839.wav", "translation": "That's a very important point.", "transcript": "所以这是一个呃非常重要的一个点。"}
{"wav_id": "101839", "speaker": "101839", "offset": "873.190", "duration": "5.710", "wav": "101839.wav", "translation": "The second conclusion is that, human beings as individuals will find it harder and harder to beat this new intelligent species AI.", "transcript": "那么第二个结论呢，作为一个个体来说，未来他会越来越难以战胜这样一个智慧物种。"}
{"wav_id": "101839", "speaker": "101839", "offset": "879.400", "duration": "8.700", "wav": "101839.wav", "translation": "For its super ability to learn from and grow on the collective human wisdom makes it invincible.", "transcript": "因为它的学习能力，它的这种知识汲取的能力，确实汇集了所有人类的智慧在里面，我们作为一个个体来说，是非常难以打败它的。"}
{"wav_id": "101839", "speaker": "101839", "offset": "888.340", "duration": "6.070", "wav": "101839.wav", "translation": "But it's comforting to know that AI can absolutely be controlled by human beings.", "transcript": "那对于人类来说的话呢，这个物种我们认为是一个完全可以控制的物种，它并不是我们不可控的。"}
{"wav_id": "101839", "speaker": "101839", "offset": "895.600", "duration": "14.110", "wav": "101839.wav", "translation": "That's to say, as a new, controllable species, in future, AI will permeate into more areas of our life, change us, enrich our experiences and reshape us.", "transcript": "那么基于这个判断，我们就可以得出，AI它是我们一个可以驾驭的新物种，而且在未来，它会越来越多的融入到我们的生活当中，去改变我们，让我们得到更高的用户体验，更大的变化。"}
{"wav_id": "101839", "speaker": "101839", "offset": "910.130", "duration": "2.300", "wav": "101839.wav", "translation": "But we must always remember what Bill Gates once said.", "transcript": "但是呢，就像比尔盖茨说的一样。"}
{"wav_id": "101839", "speaker": "101839", "offset": "913.490", "duration": "5.310", "wav": "101839.wav", "translation": "Never overestimate the change that will occur in the next two years, for there are so many difficult problems yet to be solved.", "transcript": "我们永远不要高估未来两年的变化，有非常多的问题和困难要去解决。"}
{"wav_id": "101839", "speaker": "101839", "offset": "919.280", "duration": "6.110", "wav": "101839.wav", "translation": "And never underestimate the change that will occur in the next ten, for everything might be upended.", "transcript": "但是我们也永远不要低估未来十年的这变革，它会给我们带来非常颠覆性的影响。"}
{"wav_id": "101839", "speaker": "101839", "offset": "927.920", "duration": "6.040", "wav": "101839.wav", "translation": "Here,on this precious occasion, I also want to pay tribute to Professor Marvin Minsky, the great pioneer in AI.", "transcript": "呃借这个机会呢，我们也向呃AI的前辈，就是前面提到的明斯基教授致敬。"}
{"wav_id": "101839", "speaker": "101839", "offset": "934.210", "duration": "11.400", "wav": "101839.wav", "translation": "He once said , \"The brain happens to be a meat machine\".", "transcript": "那么他有一句非常有名的话，就是The brain happens to be a meat machine就是人脑其实只是一种只是一种肉体的机器进化出来而已。"}
{"wav_id": "101839", "speaker": "101839", "offset": "945.880", "duration": "12.120", "wav": "101839.wav", "translation": "This proposition has urged our deep thinking about whether there is a fundamental difference between the silicon-based machines and the carbon-based human beings.", "transcript": "那么这个结论呢，他的这种提法呢就给我们引发了更深的思考，就是硅基的生命和我们人类的碳基生命，究竟有没有根本性的区别？"}
{"wav_id": "101839", "speaker": "101839", "offset": "959.250", "duration": "3.600", "wav": "101839.wav", "translation": "It's a question worth examining, for it leads to yet another question。", "transcript": "这是一个我们值得思考的问题，这个问题的意义就在于什么呢。"}
{"wav_id": "101839", "speaker": "101839", "offset": "963.180", "duration": "6.290", "wav": "101839.wav", "translation": "As AI advances, will it finally have an independent will?", "transcript": "就是AI它在继续往前演进的过程当中，是不是真的就不会出现独立的意志出现？"}
{"wav_id": "101839", "speaker": "101839", "offset": "970.150", "duration": "1.320", "wav": "101839.wav", "translation": "But this question I'll leave to you.", "transcript": "这个问题就留给大家思考。"}
{"wav_id": "101839", "speaker": "101839", "offset": "972.180", "duration": "0.590", "wav": "101839.wav", "translation": "Thank you!", "transcript": "谢谢大家！"}
